gimmebio/__init__.py
gimmebio/cli.py
gimmebio/constants.py
gimmebio-0.17.2.dist-info/LICENSE
gimmebio-0.17.2.dist-info/METADATA
gimmebio-0.17.2.dist-info/WHEEL
gimmebio-0.17.2.dist-info/entry_points.txt
gimmebio-0.17.2.dist-info/top_level.txt
gimmebio-0.17.2.dist-info/RECORD
