Metadata-Version: 2.1
Name: gimmebio
Version: 0.17.2
Summary: Utilities and explorations in computational biology
Home-page: UNKNOWN
Author: David Danko
Author-email: dcdanko@gmail.com
License: MIT License
Platform: UNKNOWN
Classifier: License :: OSI Approved :: MIT License
Classifier: Natural Language :: English
Classifier: Programming Language :: Python :: 3.6
Requires-Dist: future
Requires-Dist: six
Requires-Dist: gimmebio.seqs (>=0.7.0)
Requires-Dist: gimmebio.sample-seqs
Requires-Dist: gimmebio.kmers (>=0.4.0)
Requires-Dist: gimmebio.linked-reads (>=0.3.0)
Requires-Dist: gimmebio.ram-seq
Requires-Dist: gimmebio.text-plots
Requires-Dist: gimmebio.hiveplots (>=0.5.0)
Requires-Dist: gimmebio.assembly (>=0.2.1)
Requires-Dist: gimmebio.pji (>=0.1.0)
Requires-Dist: gimmebio.entropy-scores (>=0.4.0)
Requires-Dist: gimmebio.seqs
Requires-Dist: gimmebio.kmers
Requires-Dist: gimmebio.linked-reads
Requires-Dist: gimmebio.stat-strains
Requires-Dist: gimmebio.cli (>=0.1.2)
